nutils/SI.py
nutils/__init__.py
nutils/_backports.py
nutils/_graph.py
nutils/_pyast.py
nutils/_util.py
nutils/cache.py
nutils/cli.py
nutils/debug_flags.py
nutils/element.py
nutils/elementseq.py
nutils/evaluable.py
nutils/export.py
nutils/expression_v1.py
nutils/expression_v2.py
nutils/function.py
nutils/mesh.py
nutils/numeric.py
nutils/parallel.py
nutils/points.py
nutils/pointsseq.py
nutils/sample.py
nutils/solver.py
nutils/sparse.py
nutils/testing.py
nutils/topology.py
nutils/transform.py
nutils/transformseq.py
nutils/types.py
nutils/unit.py
nutils/warnings.py
nutils/matrix/__init__.py
nutils/matrix/_auto.py
nutils/matrix/_base.py
nutils/matrix/_mkl.py
nutils/matrix/_numpy.py
nutils/matrix/_scipy.py
nutils-9.1.dist-info/licenses/LICENSE
nutils-9.1.dist-info/WHEEL
nutils-9.1.dist-info/METADATA
nutils-9.1.dist-info/RECORD
