Metadata-Version: 2.4
Name: nutils
Version: 9.1
Summary: Numerical Utilities for Finite Element Analysis
Author-email: Evalf <info@evalf.com>
Requires-Python: >=3.9
Classifier: License :: OSI Approved :: MIT License
Classifier: Topic :: Scientific/Engineering :: Mathematics
Classifier: Topic :: Scientific/Engineering :: Physics
License-File: LICENSE
Requires-Dist: appdirs >=1,<2
Requires-Dist: numpy >=1.21,<3
Requires-Dist: nutils-poly >=1,<2
Requires-Dist: stringly
Requires-Dist: treelog >=1,<2
Requires-Dist: Sphinx >=1.8,<9 ; extra == "docs"
Requires-Dist: sphinx_rtd_theme >=3,<4 ; extra == "docs"
Requires-Dist: matplotlib >=3.3,<4 ; extra == "export-mpl"
Requires-Dist: meshio >=4,<6 ; extra == "import-gmsh"
Requires-Dist: mkl ; extra == "matrix-mkl"
Requires-Dist: scipy >=0.13,<2 ; extra == "matrix-scipy"
Provides-Extra: docs
Provides-Extra: export-mpl
Provides-Extra: import-gmsh
Provides-Extra: matrix-mkl
Provides-Extra: matrix-scipy
